<?xml version="1.0" standalone="yes"?>
<RECORDS>
<RECORD Id="1" Name="万物之灵" Suit1="120|15" Suit2="160|20" Suit3="240|30" SuitDesc="同时镶嵌{0}个：生命+{1} 伤害+{2}"/>
<RECORD Id="2" Name="寒冰之力" Suit1="120|15" Suit2="160|20" Suit3="240|30" SuitDesc="同时镶嵌{0}个：生命+{1} 伤害+{2}"/>
<RECORD Id="3" Name="混沌之灵" Suit1="160|20" Suit2="192|24" Suit3="288|36" SuitDesc="同时镶嵌{0}个：生命+{1} 伤害+{2}"/>
<RECORD Id="4" Name="永恒之泪" Suit1="160|20" Suit2="192|24" Suit3="288|36" SuitDesc="同时镶嵌{0}个：生命+{1} 伤害+{2}"/>
<RECORD Id="5" Name="乾坤之力" Suit1="192|24" Suit2="240|30" Suit3="320|40" SuitDesc="同时镶嵌{0}个：生命+{1} 伤害+{2}"/>
<RECORD Id="6" Name="生命之源" Suit1="192|24" Suit2="240|30" Suit3="320|40" SuitDesc="同时镶嵌{0}个：生命+{1} 伤害+{2}"/>
<RECORD Id="7" Name="太阳之灵" Suit1="240|30" Suit2="288|36" Suit3="360|45" SuitDesc="同时镶嵌{0}个：生命+{1} 伤害+{2}"/>
<RECORD Id="8" Name="烈焰之力" Suit1="240|30" Suit2="288|36" Suit3="360|45" SuitDesc="同时镶嵌{0}个：生命+{1} 伤害+{2}"/>
<RECORD Id="9" Name="暗影之力" Suit1="288|36" Suit2="360|45" Suit3="450|57" SuitDesc="同时镶嵌{0}个：生命+{1} 伤害+{2}"/>
<RECORD Id="10" Name="洪荒之力" Suit1="288|36" Suit2="360|45" Suit3="450|57" SuitDesc="同时镶嵌{0}个：生命+{1} 伤害+{2}"/>
</RECORDS>